LICENSE
MANIFEST.in
README.md
setup.py
pyriem/__init__.py
pyriem/__main__.py
pyriem/pyriem.py
pyriem.egg-info/PKG-INFO
pyriem.egg-info/SOURCES.txt
pyriem.egg-info/dependency_links.txt
pyriem.egg-info/entry_points.txt
pyriem.egg-info/requires.txt
pyriem.egg-info/top_level.txt
pyriem/plugins/__init__.py
pyriem/plugins/apache2.py
pyriem/plugins/common.py
pyriem/plugins/disk.py
pyriem/plugins/load.py
pyriem/plugins/memcache.py
pyriem/plugins/memory.py
pyriem/plugins/mysql.py
pyriem/plugins/network.py
pyriem/plugins/varnish.py