Metadata-Version: 1.0
Name: pyriem
Version: 0.1.28
Summary: A statistics collection framework for Riemann.
Home-page: http://hauntdigital.co.nz
Author: Craig Pearson
Author-email: thepearson@gmail.com
License: UNKNOWN
Platform: UNKNOWN
